{
  "generated_at": "2026-05-27T20:14:10.031564Z",
  "month": "2026-05",
  "budget": {
    "aws": 3000.0,
    "gcp": 2000.0,
    "total": 5000.0
  },
  "aws": {
    "total": 0.0,
    "services": [],
    "daily": [
      {
        "date": "2026-05-14",
        "amount": -0.0
      },
      {
        "date": "2026-05-15",
        "amount": -0.0
      },
      {
        "date": "2026-05-16",
        "amount": -0.0
      },
      {
        "date": "2026-05-17",
        "amount": -0.0
      },
      {
        "date": "2026-05-18",
        "amount": -0.0
      },
      {
        "date": "2026-05-19",
        "amount": -0.0
      },
      {
        "date": "2026-05-20",
        "amount": -0.0
      },
      {
        "date": "2026-05-21",
        "amount": -0.0
      },
      {
        "date": "2026-05-22",
        "amount": -0.0
      },
      {
        "date": "2026-05-23",
        "amount": -0.0
      },
      {
        "date": "2026-05-24",
        "amount": -0.0
      },
      {
        "date": "2026-05-25",
        "amount": -0.0
      },
      {
        "date": "2026-05-26",
        "amount": -0.0
      },
      {
        "date": "2026-05-27",
        "amount": -0.0
      }
    ]
  },
  "gcp": {
    "total": 2.31,
    "services": [
      {
        "name": "Vertex AI",
        "amount": 2.31
      }
    ],
    "daily": [
      {
        "date": "2026-05-14",
        "amount": 0.0
      },
      {
        "date": "2026-05-15",
        "amount": 0.0
      },
      {
        "date": "2026-05-16",
        "amount": 0.0
      },
      {
        "date": "2026-05-17",
        "amount": 0.0
      },
      {
        "date": "2026-05-18",
        "amount": 0.07
      },
      {
        "date": "2026-05-19",
        "amount": 0.01
      },
      {
        "date": "2026-05-20",
        "amount": 0.0
      },
      {
        "date": "2026-05-21",
        "amount": 0.0
      },
      {
        "date": "2026-05-22",
        "amount": 0.0
      },
      {
        "date": "2026-05-23",
        "amount": 0.0
      },
      {
        "date": "2026-05-24",
        "amount": 0.0
      },
      {
        "date": "2026-05-25",
        "amount": 0.0
      },
      {
        "date": "2026-05-26",
        "amount": 0.0
      }
    ]
  }
}